Workbook

Sheet Cover Sheet
A1: COMPREHENSIVE BILL OF QUANTITIES
A2: Project: Terminal 1 Expansion Project
A5: COST BREAKDOWN METHODOLOGY
A7: 1. MATERIAL COSTS
A8: Source: | B8: CIDB National Construction Cost Centre (N3C) 2024
A9: Reference: | B9: BCISM Cost Book 2022-2024 (inflated +3%)
A10: Includes: | B10: Delivery, wastage allowance (5-10% by material type)
A12: 2. LABOR COSTS
A13: Source: | B13: MBAM-CIDB Labour Wage Survey 2024
A14: Basis: | B14: Basic wage + 30% (EPF 13%, SOCSO 2%, benefits 15%)
A15: Productivity: | B15: CIDB productivity standards by trade
A16: Crew Composition: | B16: Skilled workers + helpers as per trade standards
A18: 3. EQUIPMENT/PLANT HIRE
A19: Source: | B19: CIDB N3C Machinery Hire Rates 2024
A20: Allocation: | B20: Based on work type and duration requirements
A21: Rates: | B21: Per day (8 hours), operator cost included where stated
A23: COST SUMMARY STRUCTURE
A24: Sheet 1: | B24: Cover Sheet (this page)
A25: Sheet 2: | B25: Executive Summary - Total costs with charts
A26: Sheet 3: | B26: Materials Cost Summary | C26: Detailed material breakdown
A27: Sheet 4: | B27: Labor Cost Summary | C27: Crew allocation & man-days
A28: Sheet 5: | B28: Equipment Cost Summary | C28: Plant hire requirements
A29: Sheet 6+: | B29: Detailed BOQ by Discipline | C29: Line-by-line analysis
A31: PRICING STANDARDS & REFERENCES
A32: BOQ Format: | B32: PWD Form 203A Malaysia
A33: Measurement: | B33: SMM2 (Standard Method of Measurement)
A34: Pricing Date: | B34: Q4 2024
A35: Currency: | B35: Malaysian Ringgit (RM)
A36: Validity: | B36: 60 days from date of issue
A38: EXCLUSIONS
A39: • GST/SST (apply as per prevailing tax law)
A40: • Preliminary & General items (add 8-12%)
A41: • Profit & attendance (add 10-15%)
A42: • Escalation beyond 60 days
A43: • Site-specific conditions not shown in drawings

Sheet Executive Summary
A1: EXECUTIVE SUMMARY
A3: Discipline | B3: Material (RM) | C3: Labor (RM) | D3: Equipment (RM) | E3: TOTAL (RM)
A4: ARC | B4: ='BOQ - ARC'!F8 | C4: ='BOQ - ARC'!G8 | D4: ='BOQ - ARC'!H8 | E4: ='BOQ - ARC'!I8
A5: ELEC | B5: ='BOQ - ELEC'!F7 | C5: ='BOQ - ELEC'!G7 | D5: ='BOQ - ELEC'!H7 | E5: ='BOQ - ELEC'!I7
A6: FP | B6: ='BOQ - FP'!F6 | C6: ='BOQ - FP'!G6 | D6: ='BOQ - FP'!H6 | E6: ='BOQ - FP'!I6
A7: STR | B7: ='BOQ - STR'!F8 | C7: ='BOQ - STR'!G8 | D7: ='BOQ - STR'!H8 | E7: ='BOQ - STR'!I8
A8: FINISHES & FITTINGS | E8: ='Provisional Sums'!G16
A10: GRAND TOTAL | B10: =SUM(B4:B8) | C10: =SUM(C4:C8) | D10: =SUM(D4:D8) | E10: =SUM(E4:E8)

Sheet BOQ - ARC
A1: DETAILED BOQ - ARC
A3: Item | B3: Description | C3: Qty | D3: UOM | E3: Material Rate (RM) | F3: Material Cost (RM) | G3: Labor Cost (RM) | H3: Equipment Cost (RM) | I3: Total (RM)
A4: 001 | B4: Metal Deck Roofing with Insulation | C4: 1348.5 | D4: M2 | E4: 238 | F4: =C4*E4 | G4: 0 | H4: 0 | I4: =F4+G4+H4
A5: 002 | B5: Door Set - Airport Grade | C5: 75 | D5: EA | E5: 2850 | F5: =C5*E5 | G5: 0 | H5: 0 | I5: =F5+G5+H5
A6: 003 | B6: Aluminum Window - Airport Spec | C6: 10 | D6: EA | E6: 1580 | F6: =C6*E6 | G6: 0 | H6: 0 | I6: =F6+G6+H6
A8: TOTAL - ARC | F8: =SUM(F4:F6) | G8: =SUM(G4:G6) | H8: =SUM(H4:H6) | I8: =SUM(I4:I6)

Sheet BOQ - ELEC
A1: DETAILED BOQ - ELEC
A3: Item | B3: Description | C3: Qty | D3: UOM | E3: Material Rate (RM) | F3: Material Cost (RM) | G3: Labor Cost (RM) | H3: Equipment Cost (RM) | I3: Total (RM)
A4: 001 | B4: LED Light Fixture - Airport Grade | C4: 51 | D4: EA | E4: 485 | F4: =C4*E4 | G4: 892.5 | H4: 0 | I4: =F4+G4+H4
A5: 002 | B5: 13A Power Outlet - Airport Spec | C5: 22 | D5: EA | E5: 125 | F5: =C5*E5 | G5: 308 | H5: 0 | I5: =F5+G5+H5
A7: TOTAL - ELEC | F7: =SUM(F4:F5) | G7: =SUM(G4:G5) | H7: =SUM(H4:H5) | I7: =SUM(I4:I5)

Sheet BOQ - FP
A1: DETAILED BOQ - FP
A3: Item | B3: Description | C3: Qty | D3: UOM | E3: Material Rate (RM) | F3: Material Cost (RM) | G3: Labor Cost (RM) | H3: Equipment Cost (RM) | I3: Total (RM)
A4: 001 | B4: Pipe Segment | C4: 2094.45 | D4: M | E4: 48.5 | F4: =C4*E4 | G4: 27646.74 | H4: 0 | I4: =F4+G4+H4
A6: TOTAL - FP | F6: =SUM(F4:F4) | G6: =SUM(G4:G4) | H6: =SUM(H4:H4) | I6: =SUM(I4:I4)

Sheet BOQ - STR
A1: DETAILED BOQ - STR
A3: Item | B3: Description | C3: Qty | D3: UOM | E3: Material Rate (RM) | F3: Material Cost (RM) | G3: Labor Cost (RM) | H3: Equipment Cost (RM) | I3: Total (RM)
A4: 001 | B4: IfcSpace | C4: 21777 | D4: M3 | E4: 0 | F4: =C4*E4 | G4: 0 | H4: 0 | I4: =F4+G4+H4
A5: 002 | B5: RC Slab - Airport Grade (250mm) | C5: 8608.68 | D5: M2 | E5: 285 | F5: =C5*E5 | G5: 213987.19 | H5: 70099.251 | I5: =F5+G5+H5
A6: 003 | B6: Structural Steel Column - Airport Spec | C6: 336 | D6: M | E6: 1250 | F6: =C6*E6 | G6: 43680 | H6: 51800 | I6: =F6+G6+H6
A8: TOTAL - STR | F8: =SUM(F4:F6) | G8: =SUM(G4:G6) | H8: =SUM(H4:H6) | I8: =SUM(I4:I6)

Sheet Work Packages
A1: WORK PACKAGES - CONSTRUCTION PHASING
A2: Organized by typical construction sequence for scheduling
A4: PACKAGE 1: SUBSTRUCTURE
A5: Discipline | B5: Element Type | C5: Quantity | D5: UOM | E5: Material | F5: Labor | G5: Equipment | H5: Total (RM)
A6: STR | B6: IfcColumn | C6: 336 | D6: M | E6: 420000 | F6: 43680 | G6: 51800 | H6: 515480
A7: SUBTOTAL - SUBSTRUCTURE | E7: =SUM(E6:E6) | F7: =SUM(F6:F6) | G7: =SUM(G6:G6) | H7: =SUM(H6:H6)
A9: PACKAGE 2: SUPERSTRUCTURE
A10: Discipline | B10: Element Type | C10: Quantity | D10: UOM | E10: Material | F10: Labor | G10: Equipment | H10: Total (RM)
A11: ARC | B11: IfcRoof | C11: 1348.5 | D11: M2 | E11: 320943 | F11: 0 | G11: 0 | H11: 320943
A12: STR | B12: IfcSlab | C12: 8608.68 | D12: M2 | E12: 2453473.8 | F12: 213987.19 | G12: 70099.251 | H12: 2737560.2
A13: SUBTOTAL - SUPERSTRUCTURE | E13: =SUM(E11:E12) | F13: =SUM(F11:F12) | G13: =SUM(G11:G12) | H13: =SUM(H11:H12)
A15: PACKAGE 3: MEP ROUGH-IN
A16: Discipline | B16: Element Type | C16: Quantity | D16: UOM | E16: Material | F16: Labor | G16: Equipment | H16: Total (RM)
A17: FP | B17: IfcPipeSegment | C17: 2094.45 | D17: M | E17: 101580.82 | F17: 27646.74 | G17: 0 | H17: 129227.57
A18: SUBTOTAL - MEP ROUGH-IN | E18: =SUM(E17:E17) | F18: =SUM(F17:F17) | G18: =SUM(G17:G17) | H18: =SUM(H17:H17)
A20: PACKAGE 4: FINISHES
A21: Discipline | B21: Element Type | C21: Quantity | D21: UOM | E21: Material | F21: Labor | G21: Equipment | H21: Total (RM)
A22: ARC | B22: IfcDoor | C22: 75 | D22: EA | E22: 213750 | F22: 0 | G22: 0 | H22: 213750
A23: ARC | B23: IfcWindow | C23: 10 | D23: EA | E23: 15800 | F23: 0 | G23: 0 | H23: 15800
A24: SUBTOTAL - FINISHES | E24: =SUM(E22:E23) | F24: =SUM(F22:F23) | G24: =SUM(G22:G23) | H24: =SUM(H22:H23)
A26: PACKAGE 5: MEP FINAL FIX
A27: Discipline | B27: Element Type | C27: Quantity | D27: UOM | E27: Material | F27: Labor | G27: Equipment | H27: Total (RM)
A28: ELEC | B28: IfcLightFixture | C28: 51 | D28: EA | E28: 24735 | F28: 892.5 | G28: 0 | H28: 25627.5
A29: ELEC | B29: IfcOutlet | C29: 22 | D29: EA | E29: 2750 | F29: 308 | G29: 0 | H29: 3058
A30: SUBTOTAL - MEP FINAL FIX | E30: =SUM(E28:E29) | F30: =SUM(F28:F29) | G30: =SUM(G28:G29) | H30: =SUM(H28:H29)

Sheet Provisional Sums
A1: PROVISIONAL SUMS - FINISHES & FITTINGS
A2: Items not explicitly modeled in BIM - calculated from built-up areas
A4: Item | B4: Description | C4: Qty | D4: UOM | E4: Material Rate (RM) | F4: Labor Rate (RM) | G4: Total (RM)
A5: P1 | B5: Painting - Walls and Ceilings (Dulux/Nippon 2 coats emulsion, primer, preparation) | C5: 0 | D5: M2 | E5: 8.5 | F5: 12 | G5: =C5*(E5+F5)
A6: P2 | B6: Check-in Counters & Service Desks (Solid surface, modular system, cable mgmt, branding) | C6: 15 | D6: EA | E6: 12500 | F6: 2500 | G6: =C6*(E6+F6)
A7: P3 | B7: Passenger Seating - Waiting Areas (Airport beam seating, 3-4 seater units, steel frame) | C7: 250 | D7: EA | E7: 580 | F7: 45 | G7: =C7*(E7+F7)
A8: P4 | B8: Wayfinding Signage System (Illuminated, bilingual, airport pictograms) | C8: 80 | D8: EA | E8: 650 | F8: 120 | G8: =C8*(E8+F8)
A9: P5 | B9: Flight Information Display Systems (FIDS) (55" LED, networked, real-time updates) | C9: 25 | D9: EA | E9: 8500 | F9: 1200 | G9: =C9*(E9+F9)
A10: P6 | B10: Baggage Trolley Storage Racks (Stainless steel, capacity 30 trolleys each) | C10: 12 | D10: EA | E10: 1850 | F10: 350 | G10: =C10*(E10+F10)
A11: P7 | B11: Retail Kiosk Fit-outs (Shell) (Structural frame, services rough-in, ready for tenant) | C11: 8 | D11: EA | E11: 22000 | F11: 5500 | G11: =C11*(E11+F11)
A12: P8 | B12: Rubber Safety Flooring - High Traffic (Anti-slip, heavy duty, transition zones) | C12: 1291.302 | D12: M2 | E12: 95 | F12: 28 | G12: =C12*(E12+F12)
A13: P9 | B13: Acoustic Ceiling Panels - Special Areas (High absorption, Class A, fire-rated) | C13: 1721.736 | D13: M2 | E13: 135 | F13: 42 | G13: =C13*(E13+F13)
A14: P10 | B14: Bollards & Barriers - Security (Fixed/removable, stainless steel, crash-rated) | C14: 45 | D14: EA | E14: 1250 | F14: 280 | G14: =C14*(E14+F14)
A16: TOTAL PROVISIONAL SUMS | G16: =SUM(G5:G14)

Sheet Material Summary
A1: MATERIAL COST SUMMARY
A3: Discipline | B3: IFC Class | C3: Quantity | D3: UOM | E3: Unit Rate (RM) | F3: Total Material (RM)
A4: ARC | B4: IfcRoof | C4: 1348.5 | D4: M2 | E4: 238 | F4: 320943
A5: ARC | B5: IfcDoor | C5: 75 | D5: EA | E5: 2850 | F5: 213750
A6: ARC | B6: IfcWindow | C6: 10 | D6: EA | E6: 1580 | F6: 15800
A7: ELEC | B7: IfcLightFixture | C7: 51 | D7: EA | E7: 485 | F7: 24735
A8: ELEC | B8: IfcOutlet | C8: 22 | D8: EA | E8: 125 | F8: 2750
A9: FP | B9: IfcPipeSegment | C9: 2094.45 | D9: M | E9: 48.5 | F9: 101580.82
A10: STR | B10: IfcSpace | C10: 21777 | D10: M3 | E10: 0 | F10: 0
A11: STR | B11: IfcSlab | C11: 8608.68 | D11: M2 | E11: 285 | F11: 2453473.8
A12: STR | B12: IfcColumn | C12: 336 | D12: M | E12: 1250 | F12: 420000

Sheet Labor Summary
A1: LABOR COST & CREW ALLOCATION SUMMARY
A3: Discipline | B3: IFC Class | C3: Quantity | D3: UOM | E3: Trade | F3: Crew Size | G3: Man-Days | H3: Labor Cost (RM)
A4: ELEC | B4: IfcLightFixture | C4: 51 | D4: EA | E4: Electrician (Skilled) | F4: 2 | G4: 5.1 | H4: 892.5
A5: ELEC | B5: IfcOutlet | C5: 22 | D5: EA | E5: Electrician (Skilled) | F5: 2 | G5: 1.76 | H5: 308
A6: FP | B6: IfcPipeSegment | C6: 2094.45 | D6: M | E6: Pipefitter (Skilled) | F6: 2 | G6: 167.556 | H6: 27646.74
A7: STR | B7: IfcSlab | C7: 8608.68 | D7: M2 | E7: Concrete Gang (Mixed) | F7: 6 | G7: 1475.7737 | H7: 213987.19
A8: STR | B8: IfcColumn | C8: 336 | D8: M | E8: Steel Erector (Skilled) | F8: 4 | G8: 224 | H8: 43680

Sheet Equipment Summary
A1: EQUIPMENT / PLANT HIRE SUMMARY
A3: Discipline | B3: IFC Class | C3: Equipment | D3: Duration (days) | E3: Rate/Day (RM) | F3: Total (RM)
A4: STR | B4: IfcSlab | C4: Concrete Pump Truck | D4: 73.788686 | E4: 950 | F4: 70099.251
A5: STR | B5: IfcColumn | C5: Mobile Crane 20 Tonne | D5: 28 | E5: 1850 | F5: 51800
